{"agencyType":"hybrid-emerging","displayName":"Hybrid & Emerging Models","description":"Agencies combining multiple staffing models or operating emerging models (outplacement, recruitment marketing, HR tech)","defaultPainPoints":["model-complexity","cross-model-reporting","client-expectation-management","technology-integration","market-positioning"],"recommendedAgents":["daily-briefing","client-outreach","resume-screening","candidate-sourcing"],"scoringRubric":"general","keyMetrics":["revenue-per-model","client-satisfaction","cross-sell-rate","operational-efficiency"],"commonATS":["bullhorn","lever"],"complianceLevel":"varies","typicalTeamSize":{"min":5,"max":100},"notes":"Configuration depends on which models are combined. Run /setup and describe your specific model mix for customized recommendations."}
